{"cameraMode":{"drawMode":0,"name":"Shaded","section":"Shading Mode"},"sceneLighting":true,"audioPlay":false,"sceneViewState":{"showFog":true,"showMaterialUpdate":false,"showSkybox":true,"showFlares":true,"showImageEffects":true,"showParticleSystems":true},"in2DMode":false,"pivot":{"x":75.84381103515625,"y":3.8008499145507814,"z":54.247032165527347},"rotation":{"x":-0.09134964644908905,"y":0.7079872488975525,"z":-0.09311354160308838,"w":-0.6941186189651489},"size":79.12623596191406,"orthographic":false}